flask_clacks.py
flask_clacks-1.0.1.dist-info/top_level.txt
flask_clacks-1.0.1.dist-info/METADATA
flask_clacks-1.0.1.dist-info/DESCRIPTION.rst
flask_clacks-1.0.1.dist-info/metadata.json
flask_clacks-1.0.1.dist-info/WHEEL
flask_clacks-1.0.1.dist-info/RECORD
