Metadata-Version: 2.0
Name: flask-clacks
Version: 1.0.1
Summary: A man is not dead while his name is still spoken.
Home-page: https://github.com/WilliamMayor/flask-clacks
Author: William Mayor
Author-email: mail@williammayor.co.uk
License: MIT license
Keywords: flask_clacks
Platform: any
Classifier: Development Status :: 2 - Pre-Alpha
Classifier: Intended Audience :: Developers
Classifier: License :: OSI Approved :: MIT License
Classifier: Natural Language :: English
Classifier: Programming Language :: Python
Classifier: Operating System :: OS Independent
Classifier: Topic :: Internet :: WWW/HTTP :: Dynamic Content
Classifier: Topic :: Software Development :: Libraries :: Python Modules
Requires-Dist: Flask
Provides-Extra: dev
Requires-Dist: Sphinx; extra == 'dev'
Requires-Dist: flake8; extra == 'dev'
Provides-Extra: test
Requires-Dist: pytest; extra == 'test'
Requires-Dist: coverage; extra == 'test'
Requires-Dist: tox; extra == 'test'
